{"OmegaForce":{"status":"Online","location":"Land of Trial","updatedAt":1756959878067},"FaytLE":{"status":"Online","location":"Land of Trial","updatedAt":1756959882556},"Yeiyeii":{"status":"Online","location":"Kalima 5","updatedAt":1757022193270},"LordOfGold":{"status":"Online","location":"Land of Trial","updatedAt":1756959891996},"Warrick":{"status":"Offline","location":"Devias","updatedAt":1756911207884},"Backspace":{"status":"Online","location":"Land of Trial","updatedAt":1756959900928},"Hilux":{"status":"Online","location":"Kanturu Labyrinth","updatedAt":1756911216079},"Kosmi":{"status":"Online","location":"Lost Kalima","updatedAt":1757022211994},"sayona":{"status":"Offline","location":"Kanturu Labyrinth","updatedAt":1756911225845},"KabeLj":{"status":"Online","location":"Shadow Abyss","updatedAt":1757021239810},"MARK3LOFF":{"status":"Offline","location":"Noria","updatedAt":1756911235441},"HawkEye":{"status":"Offline","location":"Noria","updatedAt":1756911240620},"YoungMiko":{"status":"Offline","location":"Kalima 5","updatedAt":1756911245106},"Pocayo":{"status":"Online","location":"Land of Trial","updatedAt":1757021820835},"Resentful":{"status":"Offline","location":"Noria","updatedAt":1756954049830},"r4mpag3":{"status":"Online","location":"Karutan 1","updatedAt":1756956089768},"Havoc":{"status":"Offline","location":"Noria","updatedAt":1756962835548},"Bagerage":{"status":"Online","location":"Noria","updatedAt":1757018090292},"Angelita":{"status":"Offline","location":"Noria","updatedAt":1756911287010},"Yves":{"status":"Offline","location":"Shadow Abyss","updatedAt":1756989609941},"Lola":{"status":"Offline","location":"Dream Land","updatedAt":1756911300002},"Blindado":{"status":"Offline","location":"Kanturu Labyrinth","updatedAt":1756911304989},"Candrias":{"status":"Online","location":"Atlans","updatedAt":1757022272856},"Iamfriend":{"status":"Online","location":"Ferea","updatedAt":1757021294937},"LovesGuys":{"status":"Online","location":"Dream Land","updatedAt":1757022286825},"LISIJS":{"status":"Online","location":"Swamp of Peace","updatedAt":1757022292523},"Ficuks":{"status":"Online","location":"Swamp of Peace","updatedAt":1757019428928},"_ILICH_":{"status":"Online","location":"Noria","updatedAt":1757021902507},"_KIUBY_":{"status":"Online","location":"Noria","updatedAt":1757022307465},"HHHH":{"status":"Offline","location":"Noria","updatedAt":1757019441926}}